teoria/semana05/exampleCodes.v
module gates(input wire [3:0] a, b, output wire [3:0] y1, y2, y3, y4, y5);

  assign y1 = a & b;    // AND
  assign y2 = a | b;    // OR
  assign y3 = a ^ b;    // XOR
  assign y4 = ~(a & b); // NAND
  assign y5 = ~(a | b); // NOR

endmodule

module sillyFunction(input wire a,b,c, output wire y);

  assign y = ~a & ~b & ~c |
              a & ~b & ~c |
              a & ~b &  c;
              
endmodule

module inv(input wire [3:0] a, output wire [3:0] y);

  assign y = ~a;

endmodule

teoria/semana05/exampleCodes_tb.v
//`include "exampleCodes.v

module testbench();


// Variables para probar el módulo gates
reg [3:0] A, B;
wire [3:0] Y1, Y2, Y3, Y4, Y5;

// Variables para probar el módulo sillyFunction
reg a1, b1, c1;
wire y;

gates U1(A, B, Y1, Y2, Y3, Y4, Y5);
sillyFunction U2(a1, b1, c1, y);

initial begin
  $display("A\tB\tY1\tY2\tY3\tY4\tY5");
  $monitor("%b\t%b\t%b\t%b\t%b\t%b\t%b", A, B, Y1, Y2, Y3, Y4, Y5);
  A = 4'b0000; B = 4'd0;
  #1 A = 4'b0001; B = 4'd1;
  #1 A = 4'd7; B = 4'd3;
end

initial begin
  #30
  $display("a b c | y");
  $display("------|--");
  $monitor("%b %b %b | %b", a1, b1, c1, y);
     a1 = 0; b1 = 0; c1 = 0;
  #1 a1 = 0; b1 = 0; c1 = 1;
  #1 a1 = 0; b1 = 1; c1 = 0;
  #1 a1 = 0; b1 = 1; c1 = 1;
  #1 a1 = 1; b1 = 0; c1 = 0;
  #1 a1 = 1; b1 = 0; c1 = 1;
  #1 a1 = 1; b1 = 1; c1 = 0;
  #1 a1 = 1; b1 = 1; c1 = 1;
end

initial
  #50 $finish;

initial begin
  $dumpfile("exampleCodes_tb.vcd");
  $dumpvars(0, testbench);
end

endmodule

teoria/semana05/exampleCodes_tb.vcd
$date
	Mon Aug  3 10:24:15 2020
$end
$version
	Icarus Verilog
$end
$timescale
	1ps
$end
$scope module testbench $end
$var wire 1 ! y $end
$var wire 4 " Y5 [3:0] $end
$var wire 4 # Y4 [3:0] $end
$var wire 4 $ Y3 [3:0] $end
$var wire 4 % Y2 [3:0] $end
$var wire 4 & Y1 [3:0] $end
$var reg 4 ' A [3:0] $end
$var reg 4 ( B [3:0] $end
$var reg 1 ) a1 $end
$var reg 1 * b1 $end
$var reg 1 + c1 $end
$scope module U1 $end
$var wire 4 , a [3:0] $end
$var wire 4 - b [3:0] $end
$var wire 4 . y1 [3:0] $end
$var wire 4 / y2 [3:0] $end
$var wire 4 0 y3 [3:0] $end
$var wire 4 1 y4 [3:0] $end
$var wire 4 2 y5 [3:0] $end
$upscope $end
$scope module U2 $end
$var wire 1 ) a $end
$var wire 1 * b $end
$var wire 1 + c $end
$var wire 1 ! y $end
$upscope $end
$upscope $end
$enddefinitions $end
#0
$dumpvars
b1111 2
b1111 1
b0 0
b0 /
b0 .
b0 -
b0 ,
x+
x*
x)
b0 (
b0 '
b0 &
b0 %
b0 $
b1111 #
b1111 "
x!
$end
#1
b1110 #
b1110 1
b1110 "
b1110 2
b1 &
b1 .
b1 %
b1 /
b1 (
b1 -
b1 '
b1 ,
#2
b1100 #
b1100 1
b1000 "
b1000 2
b11 &
b11 .
b111 %
b111 /
b100 $
b100 0
b11 (
b11 -
b111 '
b111 ,
#30
1!
0+
0*
0)
#31
0!
1+
#32
0+
1*
#33
1+
#34
1!
0+
0*
1)
#35
1+
#36
0!
0+
1*
#37
1+
