laboratorio/lab06/ejemploFFD.v
module FFD (input clk, reset, D, output reg Q);

  always @ (posedge clk or posedge reset) begin
    if (reset)
      Q <= 1'b0;
    else
      Q <= D;
  end
endmodule

// Flip Flop D de 2 bits implementado con FF de 1 bit

module FFD_2(input clk, reset, input [1:0] D, output reg [1:0] Q);

    FFD U1(clk, reset, D[1], Q[1]);
    FFD U2(clk, reset, D[0], Q[0]);

endmodule

// Flip Flop D de 2 bits implementado en 1 sólo módulo

module FFD_2 (input clk, reset, input [1:0] D, output reg [1:0] Q);

  always @ (posedge clk or posedge reset) begin
    if (reset)
      Q <= 2'b0;
    else
      Q <= D;
  end
endmodule

module FFD_2 (input clk, reset, input [1:0] D, output reg [1:0] Q);

  always @ (posedge clk or posedge reset) begin
    if (reset)
      Q <= 2'b0;
    else
      Q[1] <= D[1];
      Q[0] <= D[0];
  end
endmodule

module ejercicio1(input A, B, clk, reset, output wire Y, output wire [1:0] S_presente, S_futuro);

    // Cables necesarios para interconexiones
    wire S0_presente, S1_presente, S0_futuro, S1_futuro;
    
    // Nube combinacional del estado futuro
    assign S0_futuro = (~S1_presente & ~S0_presente & A);
    assign S1_futuro = (S0_presente & B) | (S1_presente & A & B);
    // Nube combinacional de las salidas (FSM de Mealy)
    assign Y = (S1_presente & ~S0_presente & A & B);
    
    FFD S1(.clk(clk), .reset(reset), .D(S1_futuro), .Q(S1_presente));
    FFD S0(clk, reset, S0_futuro, S0_presente);
    
    // Queremos ver los estados actuales y futuros para
    // ver si nuestra FSM funciona bien
    assign S_presente = {S1_presente, S0_presente};
    assign S_futuro = {S1_futuro, S0_futuro};

endmodule

laboratorio/lab06/testbenchFSM.v
`include "ejemploFFD.v"

module testbench();
    
    reg clk, reset, A, B;
    wire Y;
    wire [1:0] S_futuro, S_presente;
    
    ejercicio1 U1(A, B, clk, reset, Y, S_presente, S_futuro);

    initial begin
       $display("clk reset A B Sf S | Y");
       $monitor("%b %b %b %b %b %b | %b", clk, reset, A, B, S_futuro, S_presente, Y);
    end

    initial begin
        clk = 0;
        reset = 0;
        A = 0;
        B = 0;
        #1 reset = 1;
        #1 reset = 0;
        #10
        A = 1;
        B = 0;
        #20
        A = 0;
        B = 0;
        #10
        A = 1;
        B = 1;
        #30
        A = 0;
        B = 1;
    end
    
    initial
        #100 $finish;
    
    always
        #5 clk = ~clk;
        
    initial begin
        $dumpfile("timing.vcd");
        $dumpvars(0, testbench);
    end

endmodule

laboratorio/lab06/timing.vcd
$date
	Sat Sep  5 12:19:20 2020
$end
$version
	Icarus Verilog
$end
$timescale
	1s
$end
$scope module testbench $end
$var wire 1 ! Y $end
$var wire 2 " S_presente [1:0] $end
$var wire 2 # S_futuro [1:0] $end
$var reg 1 $ A $end
$var reg 1 % B $end
$var reg 1 & clk $end
$var reg 1 ' reset $end
$scope module U1 $end
$var wire 1 $ A $end
$var wire 1 % B $end
$var wire 1 ( S0_futuro $end
$var wire 1 ) S1_futuro $end
$var wire 1 ! Y $end
$var wire 1 & clk $end
$var wire 1 ' reset $end
$var wire 2 * S_presente [1:0] $end
$var wire 2 + S_futuro [1:0] $end
$var wire 1 , S1_presente $end
$var wire 1 - S0_presente $end
$scope module S0 $end
$var wire 1 ( D $end
$var wire 1 & clk $end
$var wire 1 ' reset $end
$var reg 1 - Q $end
$upscope $end
$scope module S1 $end
$var wire 1 ) D $end
$var wire 1 & clk $end
$var wire 1 ' reset $end
$var reg 1 , Q $end
$upscope $end
$upscope $end
$upscope $end
$enddefinitions $end
#0
$dumpvars
x-
x,
b0 +
bx *
0)
0(
0'
0&
0%
0$
b0 #
bx "
0!
$end
#1
0,
b0 "
b0 *
0-
1'
#2
0'
#5
1&
#10
0&
#12
b1 #
b1 +
1(
1$
#15
b0 #
b0 +
0(
b1 "
b1 *
1-
1&
#20
0&
#25
b1 #
b1 +
1(
b0 "
b0 *
0-
1&
#30
0&
#32
b0 #
b0 +
0(
0$
#35
1&
#40
0&
#42
b1 #
b1 +
1(
1%
1$
#45
0(
b10 #
b10 +
1)
b1 "
b1 *
1-
1&
#50
0&
#55
1!
b10 #
b10 +
1)
1,
b10 "
b10 *
0-
1&
#60
0&
#65
1&
#70
0&
#72
b0 #
b0 +
0)
0!
0$
#75
b0 "
b0 *
0,
1&
