laboratorio/lab04/ejemplo/codigo.v
// Ecuación a implementar: Y = (A * B * C') + (B + C)';

module gateLevel(input wire A, B, C, output wire Y);

  wire notC, w2, w3, w4;

  not (notC, C);
  and (w2, A, B, notC);
  or  (w3, B, C);
  not (w4, w3);
  or  (Y, w2, w4);

endmodule

// Función a implementar: Y = (A * B' * C) + (B + C)'

module operadores(input wire A, B, C, output wire Y);

  assign Y = (A & ~B & C) | ~(B | C);

endmodule

laboratorio/lab04/ejemplo/codigo_tb.v
// Esto es para aquellos que están usando iverilog de compilador
// Para los que usan apio pueden obviarlo
//`include "codigo.v"
// ` -> backtick
// ' -> comilla simple


module testbench();

  reg p1, p2, p3, p4, p5, p6;
  wire led1, led2;

  gateLevel   G1(p1, p2, p3, led1);
  operadores OP1(p1, p2, p3, led2);

  initial begin
    #1
    $display(" Tabla 1 y 2");
    $display("A B C | Y1 Y2");
    $display("------|------");
    $monitor("%b %b %b | %b  %b", p1, p2, p3, led1, led2);
       p1 = 0; p2 = 0; p3 = 0;
    #1 p1 = 0; p2 = 0; p3 = 1;
    #1 p1 = 0; p2 = 1; p3 = 0;
    #1 p1 = 0; p2 = 1; p3 = 1;
    #1 p1 = 1; p2 = 0; p3 = 0;
    #1 p1 = 1; p2 = 0; p3 = 1;
    #1 p1 = 1; p2 = 1; p3 = 0;
    #1 p1 = 1; p2 = 1; p3 = 1;
  end
  
  initial begin
    #9
    $display("\n");
    $display("A B C | Y");
    $display("------|--");
    $monitor("%b %b %b | %b", p4, p5, p6, led2);
       p4 = 0; p5 = 0; p6 = 0;
    #1 p4 = 0; p5 = 0; p6 = 1;
    #1 p4 = 0; p5 = 1; p6 = 0;
    #1 p4 = 0; p5 = 1; p6 = 1;
    #1 p4 = 1; p5 = 0; p6 = 0;
    #1 p4 = 1; p5 = 0; p6 = 1;
    #1 p4 = 1; p5 = 1; p6 = 0;
    #1 p4 = 1; p5 = 1; p6 = 1;
  end
  
  initial
    #20 $finish;
  
  initial begin
    $dumpfile("codigo_tb.vcd");
    $dumpvars(0, testbench);
  end
  
endmodule

laboratorio/lab04/ejemplo/codigo_tb.vcd
$date
	Fri Aug  7 16:22:03 2020
$end
$version
	Icarus Verilog
$end
$timescale
	1ps
$end
$scope module testbench $end
$var wire 1 ! led2 $end
$var wire 1 " led1 $end
$var reg 1 # p1 $end
$var reg 1 $ p2 $end
$var reg 1 % p3 $end
$var reg 1 & p4 $end
$var reg 1 ' p5 $end
$var reg 1 ( p6 $end
$scope module G1 $end
$var wire 1 # A $end
$var wire 1 $ B $end
$var wire 1 % C $end
$var wire 1 " Y $end
$var wire 1 ) notC $end
$var wire 1 * w2 $end
$var wire 1 + w3 $end
$var wire 1 , w4 $end
$upscope $end
$scope module OP1 $end
$var wire 1 & A $end
$var wire 1 ' B $end
$var wire 1 ( C $end
$var wire 1 ! Y $end
$upscope $end
$upscope $end
$enddefinitions $end
#0
$dumpvars
x,
x+
x*
x)
x(
x'
x&
x%
x$
x#
x"
x!
$end
#1
1"
1,
1)
0+
0*
0%
0$
0#
#2
0"
0,
0)
1+
1%
#3
1)
0%
1$
#4
0)
1%
#5
1"
1,
1)
0+
0%
0$
1#
#6
0"
0,
0)
1+
1%
#7
1"
1*
1)
0%
1$
#8
0"
0*
0)
1%
#9
1!
0(
0'
0&
#10
0!
1(
#11
0(
1'
#12
1(
#13
1!
0(
0'
1&
#14
1(
#15
0!
0(
1'
#16
1(
